mne_bids/__init__.py
mne_bids/config.py
mne_bids/conftest.py
mne_bids/copyfiles.py
mne_bids/dig.py
mne_bids/inspect.py
mne_bids/path.py
mne_bids/pick.py
mne_bids/read.py
mne_bids/sidecar_updates.py
mne_bids/stats.py
mne_bids/tsv_handler.py
mne_bids/utils.py
mne_bids/write.py
mne_bids/assets/help-128px.png
mne_bids/assets/help.svg
mne_bids/commands/__init__.py
mne_bids/commands/mne_bids_calibration_to_bids.py
mne_bids/commands/mne_bids_count_events.py
mne_bids/commands/mne_bids_cp.py
mne_bids/commands/mne_bids_crosstalk_to_bids.py
mne_bids/commands/mne_bids_inspect.py
mne_bids/commands/mne_bids_mark_channels.py
mne_bids/commands/mne_bids_raw_to_bids.py
mne_bids/commands/mne_bids_report.py
mne_bids/commands/run.py
mne_bids/commands/tests/test_cli.py
mne_bids/data/space-ICBM452AirSpace_fiducials.fif
mne_bids/data/space-ICBM452AirSpace_ras-vox_trans.fif
mne_bids/data/space-ICBM452AirSpace_trans.fif
mne_bids/data/space-ICBM452AirSpace_vox-mri_trans.fif
mne_bids/data/space-ICBM452Warp5Space_fiducials.fif
mne_bids/data/space-ICBM452Warp5Space_ras-vox_trans.fif
mne_bids/data/space-ICBM452Warp5Space_trans.fif
mne_bids/data/space-ICBM452Warp5Space_vox-mri_trans.fif
mne_bids/data/space-IXI549Space_fiducials.fif
mne_bids/data/space-IXI549Space_ras-vox_trans.fif
mne_bids/data/space-IXI549Space_trans.fif
mne_bids/data/space-IXI549Space_vox-mri_trans.fif
mne_bids/data/space-MNI152Lin_fiducials.fif
mne_bids/data/space-MNI152Lin_ras-vox_trans.fif
mne_bids/data/space-MNI152Lin_trans.fif
mne_bids/data/space-MNI152Lin_vox-mri_trans.fif
mne_bids/data/space-MNI152NLin2009aAsym_fiducials.fif
mne_bids/data/space-MNI152NLin2009aAsym_ras-vox_trans.fif
mne_bids/data/space-MNI152NLin2009aAsym_trans.fif
mne_bids/data/space-MNI152NLin2009aAsym_vox-mri_trans.fif
mne_bids/data/space-MNI152NLin2009aSym_fiducials.fif
mne_bids/data/space-MNI152NLin2009aSym_ras-vox_trans.fif
mne_bids/data/space-MNI152NLin2009aSym_trans.fif
mne_bids/data/space-MNI152NLin2009aSym_vox-mri_trans.fif
mne_bids-0.14.dist-info/LICENSE
mne_bids-0.14.dist-info/METADATA
mne_bids-0.14.dist-info/WHEEL
mne_bids-0.14.dist-info/entry_points.txt
mne_bids-0.14.dist-info/top_level.txt
mne_bids-0.14.dist-info/RECORD
