Metadata-Version: 2.1
Name: mne-bids
Version: 0.14
Summary: MNE-BIDS: Organizing MEG, EEG, and iEEG data according to the BIDS specification and facilitating their analysis with MNE-Python
Home-page: https://github.com/mne-tools/mne-bids
Author: mne-bids developers
Maintainer: Stefan Appelhoff
Maintainer-email: stefan.appelhoff@mailbox.org
License: BSD-3-Clause
Project-URL: Documentation, https://mne.tools/mne-bids
Project-URL: Bug Reports, https://github.com/mne-tools/mne-bids/issues
Project-URL: Source, https://github.com/mne-tools/mne-bids
Keywords: meg,eeg,ieeg,bids,brain imaging data structure,neuroscience,neuroimaging
Platform: any
Classifier: Topic :: Scientific/Engineering
Classifier: Intended Audience :: Science/Research
Classifier: Intended Audience :: Developers
Classifier: License :: OSI Approved
Classifier: Topic :: Software Development
Classifier: Topic :: Scientific/Engineering
Classifier: Operating System :: Microsoft :: Windows
Classifier: Operating System :: POSIX :: Linux
Classifier: Operating System :: MacOS
Classifier: Programming Language :: Python
Classifier: Programming Language :: Python :: 3.8
Classifier: Programming Language :: Python :: 3.9
Classifier: Programming Language :: Python :: 3.10
Classifier: Programming Language :: Python :: 3.11
Requires-Python: ~=3.8
License-File: LICENSE
Requires-Dist: mne>=1.4
Requires-Dist: numpy>=1.20.2
Requires-Dist: scipy>=1.6.3
Provides-Extra: full
Requires-Dist: nibabel>=3.2.1; extra == "full"
Requires-Dist: pybv>=0.7.5; extra == "full"
Requires-Dist: eeglabio>=0.0.2; extra == "full"
Requires-Dist: pymatreader>=0.0.30; extra == "full"
Requires-Dist: matplotlib>=3.4.0; extra == "full"
Requires-Dist: pandas>=1.2.4; extra == "full"
Requires-Dist: EDFlib-Python>=1.0.6; extra == "full"
